micropython_magic/__init__.py
micropython_magic/exp_magics.py
micropython_magic/interactive.py
micropython_magic/logger.py
micropython_magic/magic_transformer.py
micropython_magic/memoryinfo.py
micropython_magic/mpr.py
micropython_magic/octarine.py
micropython_magic/param_fixup.py
micropython_magic/script_access.py
micropython_magic/scripts/fw_info.py
micropython_magic-0.10.2.dist-info/LICENSE
micropython_magic-0.10.2.dist-info/METADATA
micropython_magic-0.10.2.dist-info/WHEEL
micropython_magic-0.10.2.dist-info/RECORD
