Metadata-Version: 2.1
Name: micropython-magic
Version: 0.10.2
Summary: MicroPython Magic commands for use with Jupyter notebooks and Jupyter Labs
License: MIT
Keywords: MicroPython,stubs,Jupyter,notebooks,Jupyter Labs,vscode
Author: Jos Verlinde
Author-email: jos_verlinde@hotmail.com
Requires-Python: >=3.8,<4.0
Classifier: License :: OSI Approved :: MIT License
Classifier: Programming Language :: Python :: 3
Classifier: Programming Language :: Python :: 3.8
Classifier: Programming Language :: Python :: 3.9
Classifier: Programming Language :: Python :: 3.10
Classifier: Programming Language :: Python :: 3.11
Provides-Extra: widgets
Requires-Dist: ipympl (>=0.9.3,<0.10.0)
Requires-Dist: loguru (>=0.7.2,<0.8.0)
Requires-Dist: mpremote (>=1.22.0,<2.0.0)
